multipageforms/__init__.py
multipageforms/apps.py
multipageforms/models.py
multipageforms/tools.py
multipageforms/forms/__init__.py
multipageforms/forms/multiform.py
multipageforms/forms/multipageform.py
multipageforms/views/__init__.py
multipageforms/views/generic.py
django_multipageforms-0.7.0.dist-info/LICENSE.txt
django_multipageforms-0.7.0.dist-info/METADATA
django_multipageforms-0.7.0.dist-info/WHEEL
django_multipageforms-0.7.0.dist-info/top_level.txt
django_multipageforms-0.7.0.dist-info/RECORD
